TPM_Service-1.0.0.dist-info/METADATA
TPM_Service-1.0.0.dist-info/RECORD
TPM_Service-1.0.0.dist-info/WHEEL
TPM_Service-1.0.0.dist-info/top_level.txt
tpm_service/__init__.py
tpm_service/app.py
tpm_service/auth.py
tpm_service/config.py
tpm_service/setup.py
tpm_service/tpm_actions.py
tpm_service/tpm_policys.py
tpm_service/tpm_server.py
tpm_service/tpm_utils.py
tpm_service/usage.py
tpm_service/views.py
