Metadata-Version: 2.1
Name: TPM-Service
Version: 1.0.0
Summary: Provide restful api service for TPM
Home-page: UNKNOWN
Author: wenzt2
Author-email: wenzt2@lenovo.com
License: UNKNOWN
Platform: linux
Classifier: Intended Audience :: Developers
Classifier: Programming Language :: Python
Classifier: Programming Language :: Python :: 2.7
Requires-Dist: Flask (==1.1.1)
Requires-Dist: Flask-RESTful (==0.3.7)
Requires-Dist: Flask-SQLAlchemy (==2.4.0)
Requires-Dist: Flask-Login (==0.4.1)
Requires-Dist: passlib (==1.7.1)
